{
  "$schema": "https://cashtokens.org/bcmr-v2.schema.json",
  "version": { "major": 1, "minor": 0, "patch": 0 },
  "latestRevision": "2024-26-11T19:36:00.912Z",
  "registryIdentity": {
    "name": "The Real ₿Coin",
    "description": "self-published bcmr for DogeCash"
  },
  "identities": {
    "8473d94f604de351cdee3030f6c354d36b257861ad8e95bbc0a06fbab2a2f9cf": {
      "2023-05-15T14:14:03.145Z": {
        "name": "₿Coin",
        "description": "Lets overtake the ₿Coin Price",
        "token": {
          "category": "8473d94f604de351cdee3030f6c354d36b257861ad8e95bbc0a06fbab2a2f9cf",
          "symbol": "₿",
          "decimals": 6
        },
        "uris": {
          "icon": "https://github.com/martin9020/Satoshi/blob/main/Bitcoin.png"
        }
      }
    }
  }
}
